[
    {
        "id": 3000,
        "name": "עוגיות",
        "description": "מקרונס קסיס ( מארז 12 יח')",
        "price": 54,
        "image": "Roladin-00333.jpg",
        "type": "חלבי",
        "Component": "גאנש קסיס ושוקולד לבן"
    },
    {
        "id": 3001,
        "name": "עוגיות",
        "description": "עוגיות בייגלך",
        "price": 38,
        "image": "talzip-roladin-11-22-2-2531-mrz_websize-1024x683.jpg",
        "type": "פרווה",
        "Component": "עוגיות מלוחות בשילוב שומשום וקצח."
    },
    {
        "id": 3002,
        "name": "עוגיות",
        "description": "קרקר עם שומשום ושמן זית",
        "price": 38,
        "image": "קרקר עם שומשום ושמן זית.jpg",
        "type": "פרווה",
        "Component": ""
    },
    {
        "id": 3003,
        "name": "עוגיות",
        "description": "BOBO DARK COOKIES",
        "price": 16,
        "image": "BOBO DARK COOKIES.png",
        "type": "חלבי",
        "Component": "עוגיית שוקולד בשילוב שוקולד מריר, שוקולד חלב ושוקולד לבן מקורמל"
    },
    {
        "id": 3004,
        "name": "עוגיות",
        "description": "BOBO WHITE COOKIES",
        "price": 16,
        "image": "BOBO WHITE COOKIES.jpg",
        "type": "חלבי",
        "Component": "עוגיית שוקולד בשילוב שוקולד מריר, שוקולד חלב ושוקולד לבן מקורמל"
    },
    {
        "id": 3005,
        "name": "עוגיות",
        "description": "עוגיית דגנים וחמוציות ללא סוכר",
        "price": 38,
        "image": "עוגיית דגנים וחמוציות ללא סוכר.jpg",
        "type": "חלבי",
        "Component": ""
    },
    {
        "id": 3006,
        "name": "עוגיות",
        "description": "עוגיות חמאה תפוז",
        "price": 44,
        "image": "עוגיות חמאה תפוז.jpg",
        "type": "חלבי",
        "Component": "עוגיות חמאה תפוז ללא גלוטן"
    },
    {
        "id": 3007,
        "name": "עוגיות",
        "description": "עוגיות קפה",
        "price": 44,
        "image": "עוגיות קפה.jpg",
        "type": "חלבי",
        "Component": "עוגיות קפה ללא גלוטן"
    },
    {
        "id": 3008,
        "name": "עוגיות",
        "description": "מקרונס פיסטוק ( מארז 12 יח')",
        "price": 54,
        "image": "Roladin-00333.jpg",
        "type": "חלבי",
        "Component": "גאנש פיסטוק ושוקולד לבן"
    },
    {
        "id": 3009,
        "name": "עוגיות",
        "description": "דיימונד לימון שקדים",
        "price": 38,
        "image": "דיימונד לימון שקדים.jpg",
        "type": "חלבי",
        "Component": "מארז עוגיות חמאה בנגיעות לימון ושקדים"
    },
    {
        "id": 3010,
        "name": "עוגיות",
        "description": "מקרונס אינפיניטי וניל ( מארז 12 יח')",
        "price": 54,
        "image": "Roladin-00333.jpg",
        "type": "חלבי",
        "Component": "גאנש וניל מדגסקר ושוקולד לבן"
    },
    {
        "id": 3011,
        "name": "עוגיות",
        "description": "סהרוני שקדים",
        "price": 38,
        "image": "סהרוני שקדים.jpg",
        "type": "חלבי",
        "Component": ""
    },
    {
        "id": 3012,
        "name": "עוגיות",
        "description": "מארז 3 עוגיות BOBO WHITE COOKIES",
        "price": 48,
        "image": "מארז 3 עוגיות BOBO WHITE COOKIES.jpg",
        "type": "חלבי",
        "Component": "עוגיית שוקולד בשילוב שוקולד מריר, שוקולד חלב ושוקולד לבן מקורמל"
    },
    {
        "id": 3013,
        "name": "עוגיות",
        "description": "עוגיות ריבה",
        "price": 38,
        "image": "עוגיות ריבה.jpg",
        "type": "חלבי",
        "Component": "מארז עוגיות מבצק חמאה פריך במילוי ריבת תות"
    },
    {
        "id": 3014,
        "name": "עוגיות",
        "description": "מיני בראוניז",
        "price": 46,
        "image": "מיני בראוניז.jpg",
        "type": "חלבי",
        "Component": "מארז עוגיות מיני בראוניז רכות ונימוחות"
    },
    {
        "id": 3015,
        "name": "עוגיות",
        "description": "עוגיות פקאן ללא תוספת סוכר",
        "price": 38,
        "image": "עוגיות פקאן ללא תוספת סוכר.jpg",
        "type": "חלבי",
        "Component": "מארז עוגיות מבצק חמאה פריך עם פקאן ללא תוספת סוכר"
    },
    {
        "id": 3016,
        "name": "עוגיות",
        "description": "עוגיות דאבל צ'אנקס",
        "price": 42,
        "image": "עוגיות דאבל צ'אנקס.png",
        "type": "חלבי",
        "Component": "מארז עוגיות חמאה קקאו בשילוב צ'אנקס חלב ומריר"
    },
    {
        "id": 3017,
        "name": "עוגיות",
        "description": "מארז 3 עוגיות BOBO DARK COOKIES",
        "price": 48,
        "image": "מארז 3 עוגיות BOBO DARK COOKIES.png",
        "type": "חלבי",
        "Component": "עוגיית שוקולד חמאה בתוספת צ'אנקס שוקולד חלב"
    },
    {
        "id": 3019,
        "name": "עוגיות",
        "description": "עוגיות אלפחורס",
        "price": 42,
        "image": "אלפחורס.png",
        "type": "חלבי",
        "Component": "מארז עוגיות מבצק חמאה פריך במילוי ריבת חלב וציפוי קוקוס"
    },
    {
        "id": 3020,
        "name": "עוגיות",
        "description": "עוגיות חמאה ללא תוספת סוכר",
        "price": 38,
        "image": "עוגיות חמאה ללא תוספת סוכר.jpg",
        "type": "חלבי",
        "Component": "מארז עוגיות מבצק חמאה פריך ללא תוספת סוכר"
    },
    {
        "id": 3021,
        "name": "עוגיות",
        "description": "עוגיות סבתא תמרים",
        "price": 42,
        "image": "עוגיות סבתא תמרים.jpg",
        "type": "חלבי",
        "Component": "מארז עוגיות מבצק שמנת במילוי תמרים"
    },
    {
        "id": 4000,
        "name": "מן המעדניה",
        "description": "יין אדום מרלו",
        "price": 58,
        "image": "יין אדום מרלו.jpg",
        "type": "פרווה",
        "Component": "יין אדום מרלו. כשר לפסח."
    },
    {
        "id": 4001,
        "name": "מן המעדניה",
        "description": "ממרח פלפלונים ישראלים חריפים",
        "price": 24,
        "image": "ממרח פלפלונים ישראלים חריפים.jpg",
        "type": "פרווה",
        "Component": "פלפלונים ירוקים חריפים כבושים (60%), שמן זית ולימון"
    },
    {
        "id": 4002,
        "name": "מן המעדניה",
        "description": "פסטו מבזיליקום טרי",
        "price": 24,
        "image": "פסטו מבזיליקום טרי.jpg",
        "type": "פרווה",
        "Component": ""
    },
    {
        "id": 4003,
        "name": "מן המעדניה",
        "description": "טפנד זיתים ירוקים עם עלי אורגנו",
        "price": 24,
        "image": "טפנד זיתים ירוקים עם עלי אורגנו.jpg",
        "type": "פרווה",
        "Component": "עלול להכיל שאריות חרצנים, מכיל קליפת וגרעיני לימון"
    },
    {
        "id": 4004,
        "name": "מן המעדניה",
        "description": "ממרח ארטישוק עם נגיעות כמהין",
        "price": 24,
        "image": "ממרח ארטישוק עם נגיעות כמהין.jpg",
        "type": "פרווה",
        "Component": "מכיל קליפת וגרעיני לימון"
    },
    {
        "id": 4005,
        "name": "מן המעדניה",
        "description": "ריבת בצלים סגולים וסומק ביין קברנה סוביניון",
        "price": 22,
        "image": "ריבת בצלים סגולים וסומק ביין קברנה סוביניון.jpg",
        "type": "פרווה",
        "Component": "מכיל קליפת וגרעיני לימון , מכיל אלכוהול (0.4%)"
    },
    {
        "id": 5000,
        "name": "פרווה",
        "description": "קייקס פרג שוקולד",
        "price": 49,
        "image": "talzip-roladin-2-22-214152hrz-1.jpg",
        "type": "פרווה",
        "Component": "עוגת פרג, שקדים ושוקולד"
    },
    {
        "id": 5001,
        "name": "פרווה",
        "description": "פס מרקיז שוקולד",
        "price": 69,
        "image": "מרקיז-פס-1.jpg",
        "type": "פרווה",
        "Component": "ביסקוויט קקאו, מוס שוקולד מריר קרמל וקרנץ' פרלינה"
    },
    {
        "id": 5002,
        "name": "פרווה",
        "description": "מרקיז שוקולד (קוטר 21)",
        "price": 159,
        "image": "ללא_תמונה.png",
        "type": "פרווה",
        "Component": "ביסקוויט קקאו, מוס שוקולד מריר קרמל וקרנץ' פרלינה"
    },
    {
        "id": 5003,
        "name": "פרווה",
        "description": "פס מוס אספרסו אגוזים",
        "price": 69,
        "image": "פס מוס אספרסו אגוזים.jpg",
        "type": "פרווה",
        "Component": "ביסקוויט אגוזי מלך ושוקולד צ'יפס טבול בסירופ אספרסו, גנאש שוקולד ומוס שוקולד קפה"
    },
    {
        "id": 11000,
        "name": "פטיסרי",
        "description": "מארז 4 פטיסרי",
        "price": 32,
        "image": "מארז 4 פטיסרי.jpg",
        "type": "חלבי",
        "Component": "4 סוגי פטיסרי לבחירה:Pure Chocolate, פטיסרי אישי פרזייה, פטיסרי פיסטוק, קרמליו, מילפיי אישי, סופלה"
    },
    {
        "id": 11001,
        "name": "פטיסרי",
        "description": "קרמליו",
        "price": 32,
        "image": "קרמליו.jpg",
        "type": "חלבי",
        "Component": "ביסקוויט קרמל, קרמו קרמל, קריספי שוקולד חלב, מוס קרמל ושונטי שוקולד לבן"
    },
    {
        "id": 11002,
        "name": "פטיסרי",
        "description": "מילפיי לב",
        "price": 65,
        "image": "מילפיי לב.jpg",
        "type": "חלבי",
        "Component": "בצק עלים עשיר בחמאה במילוי קרם פטיסייר שמנת"
    },
    {
        "id": 11003,
        "name": "פטיסרי",
        "description": "לב רושרס שוקולד",
        "price": 65,
        "image": "לב רושרס שוקולד.jpg",
        "type": "חלבי",
        "Component": "ביסקוויט קקאו, מוס שוקולד, בציפוי קרנצ'י שוקולד חלב ואגוזי לוז"
    },
    {
        "id": 11004,
        "name": "פטיסרי",
        "description": "פטיסרי Pistachio lvory",
        "price": 32,
        "image": "פטיסרי Pistachio lvory.jpg",
        "type": "חלבי",
        "Component": "קרוקנט פיסטוק, קרמו וניל, פיננסייר שקדים, מרמלדת פטל ומוס פיסטוק"
    },
    {
        "id": 11005,
        "name": "פטיסרי",
        "description": "סופלה שוקולד בלגי",
        "price": 24,
        "image": "סופלה שוקולד.jpg",
        "type": "חלבי",
        "Component": ""
    },
    {
        "id": 11006,
        "name": "פטיסרי",
        "description": "פחזניות קרם שניטלי וניל",
        "price": 55,
        "image": "פחזניות קרם שנטילי וניל.jpg",
        "type": "חלבי",
        "Component": "מארז של פחזניות בצק רבוך במילוי קרם שנטילי וניל"
    },
    {
        "id": 11007,
        "name": "פטיסרי",
        "description": "מארז כדורי שוקולד",
        "price": 42,
        "image": "מארז כדורי שוקולד.png",
        "type": "חלבי",
        "Component": "מארז של כדורי שוקולד איכותי בשילוב עם קוקוס"
    },
    {
        "id": 10000,
        "name": "עוגות עגולות",
        "description": "מוס מנגוליה מנגו (קוטר 16)",
        "price": 110,
        "image": "מוס מנגוליה מנגו.png",
        "type": "חלבי",
        "Component": "פיננסייר שקדים, קרמו מנגו פסיפלורה, קריספי פייטה ומוס שמנת שוקולד לבן"
    },
    {
        "id": 10001,
        "name": "עוגות עגולות",
        "description": "מוס Black Cookie Cream (קוטר 21)",
        "price": 159,
        "image": "מוס Black Cookie Cream.jpg",
        "type": "חלבי",
        "Component": "בראוניז שוקולד, קרם גבינת שמנת ועוגיות OREO."
    },
    {
        "id": 10002,
        "name": "עוגות עגולות",
        "description": "Pistachio Ivory (קוטר 16)",
        "price": 129,
        "image": "Pistachio Ivory.jpg",
        "type": "חלבי",
        "Component": "ביסקוויט פיסטוק, מוס וניל, קריספי פיסטוק ושונטי שוקולד לבן ופיסטוק"
    },
    {
        "id": 10003,
        "name": "עוגות עגולות",
        "description": "מוס קרמו שוקולד (קוטר 16)",
        "price": 110,
        "image": "מוס קרמו שוקולד.png",
        "type": "חלבי",
        "Component": "ביסקוויט שוקולד, קרמו שוקולד בלגי, קראנץ פייטה ומוס שוקולד מריר"
    },
    {
        "id": 10004,
        "name": "עוגות עגולות",
        "description": "מוס טריקולד(קוטר 21)",
        "price": 159,
        "image": "מוס טריקולד.png",
        "type": "חלבי",
        "Component": "שכבות של מוס מריר, חלב ולבן על תחתית אפויה"
    },
    {
        "id": 10005,
        "name": "עוגות עגולות",
        "description": "מוס ברולה קרמל (קוטר 21)",
        "price": 159,
        "image": "מוס ברולה קרמל.jpg",
        "type": "חלבי",
        "Component": "מוס שוקולד לבן וקרמו קרמל על תחתית בראוניז שוקולד בשילוב קראנץ רושה בציפוי גנאש קרמל שוקולד לבן"
    },
    {
        "id": 7000,
        "name": "עוגות פס",
        "description": "פס פאדג' נואר",
        "price": 69,
        "image": "פס פאדג' נואר.jpg",
        "type": "חלבי",
        "Component": "פאדג' שוקולד אפוי, קרמו שוקולד מריר ושונטי שוקולד חלב"
    },
    {
        "id": 7001,
        "name": "עוגות פס",
        "description": "פס תפוחים ללא תוספת סוכר",
        "price": 69,
        "image": "פס תפוחים ללא תוספת סוכר.jpg",
        "type": "חלבי",
        "Component": "בצק פריך שקדים, מלית תפוחים עם קינמון ושטרוייזל בשילוב פלחי תפוחים ופקאן"
    },
    {
        "id": 7002,
        "name": "עוגות פס",
        "description": "פס מרנג גבינה ולימון",
        "price": 69,
        "image": "פס מרנג גבינה ולימון.jpg",
        "type": "חלבי",
        "Component": "קרמבל גבינת שמנת, גבינת שמנת אפויה, קרם לימון, קרם שונטי ונשיקות מרנג."
    },
    {
        "id": 7003,
        "name": "עוגות פס",
        "description": "פס מילפיי וניל",
        "price": 75,
        "image": "פס מילפיי וניל.jpg",
        "type": "חלבי",
        "Component": "בצק עלים עשיר בחמאה במילוי קרם פטיסייר שמנת."
    },
    {
        "id": 7004,
        "name": "עוגות פס",
        "description": "פס מוס גבינה פירורים",
        "price": 69,
        "image": "פס מוס גבינה פירורים.jpg",
        "type": "חלבי",
        "Component": "סבלה ברטון, קרם גבינה וקרמבל חמאה."
    },
    {
        "id": 7005,
        "name": "עוגות פס",
        "description": "פס גבינה אפויה ללא תוספת סוכר",
        "price": 69,
        "image": "פס גבינה אפויה ללא תוספת סוכר.jpg",
        "type": "חלבי",
        "Component": "גבינה אפויה על בצק פריך, קרם שמנת ושטרוייזל שקדים, ללא תוספת סוכר."
    },
    {
        "id": 7006,
        "name": "עוגות פס",
        "description": "פס רושרס שוקולד",
        "price": 69,
        "image": "פס רושרס שוקולד.png",
        "type": "חלבי",
        "Component": "דקואז' שקדים ואגוזי לוז, ביסקוויט שוקולד, קרמו שוקולד פרלינה בציפוי קראסט אגוזי לוז ושונטי נוצ'ולה"
    },
    {
        "id": 7007,
        "name": "עוגות פס",
        "description": "פס מוס טרמיסו",
        "price": 69,
        "image": "פס מוס טרמיסו.jpg",
        "type": "חלבי",
        "Component": " קרם מסקרפונה, ביסקוויט שוקולד שקדים, גנאש שוקולד קפה,בישקוטים באספרסו, אמרטו וקקאו."
    },
    {
        "id": 7008,
        "name": "עוגות פס",
        "description": "פס רושרס פיסטוק",
        "price": 69,
        "image": "פס רושרס פיסטוק.jpg",
        "type": "חלבי",
        "Component": "דקואז' פיסטוק, ג'לה פטל, ביסקוויט שוקולד לבן, מוס שוקולד לבן בציפוי קראסט שקדי פיסטוק"
    },
    {
        "id": 7009,
        "name": "עוגות פס",
        "description": "פס White cream cheese",
        "price": 69,
        "image": "פס White cream cheese.jpg",
        "type": "חלבי",
        "Component": "סבלה ברטון, גבינה אפויה, שוקולד לבן ושונטי וניל."
    },
    {
        "id": 7010,
        "name": "עוגות פס",
        "description": "פס קרמבל תפוחים",
        "price": 69,
        "image": "פס קרמבל תפוחים.png",
        "type": "חלבי",
        "Component": "תחתית בצק פריך שקדים, ריבת משמש במילוי תפוחי עץ, צימוקים, קינמון וקרמבל שקדים"
    },
    {
        "id": 7011,
        "name": "עוגות פס",
        "description": "פס Black cookie cream",
        "price": 69,
        "image": "פס Black cookie cream.jpg",
        "type": "חלבי",
        "Component": "בראוניז שוקולד, קרם גבינת שמנת, עוגיות OREO."
    },
    {
        "id": 7012,
        "name": "עוגות פס",
        "description": "פס מוס טריקולד",
        "price": 69,
        "image": "פס מוס טריקולד.png",
        "type": "חלבי",
        "Component": "שכבות של מוס שוקולד בלגי מריר, חלב ולבן על ביסקוויט קקאו"
    },
    {
        "id": 7013,
        "name": "עוגות פס",
        "description": "פס מוס אספרסו אגוזים",
        "price": 69,
        "image": "פס מוס אספרסו אגוזים.jpg",
        "type": "פרווה",
        "Component": "ביסקוויט אגוזי מלך ושוקולד צ'יפס טבול בסירופ אספרסו, גנאש שוקולד ומוס שוקולד קפה"
    },
    {
        "id": 6000,
        "name": "מאפים מתוקים",
        "description": "גביניות ריקוטה",
        "price": 38,
        "image": "גביניות-ריקוטה.png",
        "type": "חלבי",
        "Component": "בצק שמרים חמאה במילוי גבינת ריקוטה"
    },
    {
        "id": 6001,
        "name": "מאפים מתוקים",
        "description": "יחידות קרולדין וניל",
        "price": 30,
        "image": "יחידות קרולדין וניל.jpg",
        "type": "חלבי",
        "Component": "קרואסון חמאה מטוגן במילוי קרם פטיסייר וניל בקראסט סוכר וניל"
    },
    {
        "id": 6002,
        "name": "מאפים מתוקים",
        "description": "מארז מיקס מאפים מתוקים",
        "price": 57,
        "image": "מארז מיקס מאפים מתוקים.jpg",
        "type": "חלבי",
        "Component": "מארז 15 יח' מכיל: 3 יח' קרואסון שוקולד, 3 יח' חמאה, 3 גבניות, 3 יח' שנק פיסטוק, 3 יח' דייניש תפוחים"
    },
    {
        "id": 6003,
        "name": "מאפים מתוקים",
        "description": "קרואסון חמאה",
        "price": 29,
        "image": "קרואסון חמאה.jpg",
        "type": "חלבי",
        "Component": ""
    },
    {
        "id": 9000,
        "name": "טארטים",
        "description": "טארט פקאן",
        "price": 75,
        "image": "טארט פקאן.jpg",
        "type": "חלבי",
        "Component": "סבלה פריך, אגוזי מלך ופקאן בטופי קרמל"
    },
    {
        "id": 9001,
        "name": "טארטים",
        "description": "טארט פרג",
        "price": 65,
        "image": "טארט פרג.png",
        "type": "חלבי",
        "Component": "סבלה פריך, מלית פרג, קרם שקדים ורום ושקדים פרוסים"
    },
    {
        "id": 8000,
        "name": "עוגות בחושות",
        "description": "בראוניז",
        "price": 46,
        "image": "בראוניז.jpg",
        "type": "חלבי",
        "Component": "עוגת בראוניז שוקולד עסיסית"
    },
    {
        "id": 8001,
        "name": "עוגות בחושות",
        "description": "קייקס מסיבת שוקולד",
        "price": 56,
        "image": "קייקס מסיבת שוקולד.jpg",
        "type": "חלבי",
        "Component": "עוגת שוקולד בציפוי גאנש שוקולד חלב ומריר וסוכריות צבעוניות."
    },
    {
        "id": 8002,
        "name": "עוגות בחושות",
        "description": "קייקס תפוז קוקוס",
        "price": 49,
        "image": "קייקס תפוז קוקוס.jpg",
        "type": "חלבי",
        "Component": "עוגת תפוזים בסגנון צרפתי בציפוי קוקוס"
    },
    {
        "id": 8003,
        "name": "עוגות בחושות",
        "description": "קייקס לימון פירות יער",
        "price": 52,
        "image": "קייקס לימון פירות יער.jpg",
        "type": "חלבי",
        "Component": "עוגת לימון בתוספת פירות יער ושקדים מולבנים פרוסים"
    },
    {
        "id": 8004,
        "name": "עוגות בחושות",
        "description": "קייקס בטעם מייפל",
        "price": 52,
        "image": "קייקס בטעם מייפל.jpg",
        "type": "חלבי",
        "Component": "עוגה בטעם מייפל בתוספת שברי פקאן"
    },
    {
        "id": 800,
        "name": "מגשי ארוח",
        "description": "סלט בורגול",
        "price": 138,
        "image": "בורגול.JPG",
        "type": "חלבי",
        "Component": "8 יח' סלט בורגול ועשבי תיבול בכוסות אישיות - חסה לליק, בורגול, נענע ופטרוזיליה, חמוציות, קוביות גבינה בולגרית ושקדים קלויים בתוספת רוטב שמן זית לימון."
    },
    {
        "id": 801,
        "name": "מגשי ארוח",
        "description": "מגש פודינג צ'יה",
        "price": 158,
        "type": "פרווה",
        "Component": "פודינג זרעי צ'יה, פירות טריים חתוכים בהתאם לעונה, שערות חלווה ושקדים קלויים - 18 יח'",
        "image": "./פודינג-ציה-לאתר-1024x669.jpg"
    },
    {
        "id": 802,
        "name": "מגשי ארוח",
        "description": "כריכוני מיני ביס לחם לבן",
        "price": 188,
        "type": "פרווה",
        "Component": "כריכוני ביס בטעמים קפרזה ואנטיפסטי ( טבעוני) - 16 יח'.",
        "image": "./כריכוני-מיני-ביס-לבן-לאתר-1024x678.jpg"
    },
    {
        "id": 803,
        "name": "מגשי ארוח",
        "description": "סלט אסייאתי ",
        "price": 138,
        "type": "פרווה",
        "Component": "8 יח' סלט אסיאתי בכוסות אישיות- אטריות שעועית, אצות ווקאמה, גזר, צנונית, מלפפון ירוק, פולי סויה, צ'ילי אדום, עלי נענע ובוטנים גרוסים בתוספת רוטב אסייאתי.",
        "image": "./סלט-אסיאתי-לאתר-1024x674.jpg"
    },
    {
        "id": 804,
        "name": "מגשי ארוח",
        "description": " סלט קיסר",
        "price": 138,
        "type": "חלבי",
        "Component": "8 יח' סלט קיסר רענן בכוסות אישיות - חסה לליק, בצל פריך, ביצה קשה, גבינת פרמז'ן וקרוטונים מגיע בתוספת רוטב קיסר.",
        "image": "./סלט-קיסר-לאתר-1024x676.jpg"
    },
    {
        "id": 805,
        "name": "מגשי ארוח",
        "description": "רולדיניו 30 יח'",
        "price": 188,
        "type": "פרווה",
        "Component": "מיני רול טורטיה 2 סוגים לבחירה.",
        "image": "./רולדיניו-לאתר-1024x682.jpg"
    },
    {
        "id": 900,
        "name": "לחמי מחמצת",
        "description": "לחם מחמצת כוסמין",
        "price": 24,
        "type": "פרווה",
        "Component": "לחם מחמצת על בסיס קמח כוסמין בתוספת דגנים",
        "image": "כוסמין.jpg"
    },
    {
        "id": 901,
        "name": "לחמי מחמצת",
        "description": "לחם מחמצת דגנים",
        "price": 24,
        "type": "פרווה",
        "Component": "לחם מחמצת עם קמח שיפון וקמח מלא בתוספת דגנים שונים  אזהרה: סכנת חנק לילדים מתחת לגיל 5 עלול להכיל קליפות דגנים",
        "image": "דגנים.jpg"
    },
    {
        "id": 902,
        "name": "לחמי מחמצת",
        "description": " לחם מחמצת זיתים ",
        "price": 24,
        "type": "פרווה",
        "Component": "לחם מחמצת עם קמח מלא בתוספת זיתי קלמטה",
        "image": "talzip5802-1.jpg"
    },
    {
        "id": 903,
        "name": "לחמי מחמצת",
        "description": "לחם מחמצת פרג",
        "price": 22,
        "type": "פרווה",
        "Component": "לחם מחמצת עם קמח מלא בתוספת פרג",
        "image": "פרג.jpg"
    },
    {
        "id": 904,
        "name": "לחמי מחמצת",
        "description": "לחם מחמצת סלק",
        "price": 26,
        "type": "פרווה",
        "Component": "לחם מחמצת בתוספת קמח שיפון וסלק   עלול להכיל קליפות אגוזים ",
        "image": "סלק.jpg"
    },
    {
        "id": 905,
        "name": "לחמי מחמצת",
        "description": "לחם מחמצת אגוזים וצימוקים",
        "price": 24,
        "type": "פרווה",
        "Component": "לחם מחמצת עם קמח מלא וקמח שיפון בתוספת אגוזי מלך וצימוקים  אזהרה: סכנת חנק לילדים מתחת לגיל 5 עלול להכיל קליפות אגוזים",
        "image": "אגוזים_צימוקים.jpg"
    },
    {
        "id": 906,
        "name": "לחמי מחמצת",
        "description": " לחם מחמצת קל",
        "price": 19,
        "type": "פרווה",
        "Component": "לחם מחמצת בתוספת קמח מלא מופחת קלוריות",
        "image": "לחם-קל-1024x683.jpg"
    },
    {
        "id": 100,
        "name": "מאפים מלוחים",
        "description": "מאפה קשקבלמי",
        "price": 25,
        "type": "חלבי",
        "Component": "בצק פריך קשקבל במילוי גבינת קשקבל מלוחהות",
        "image": "DROR1075.jpg"
    },
    {
        "id": 101,
        "name": "מאפים מלוחים",
        "description": "מאפה קשקבל מאפה קשקבל הוסף להזמנה חלבי",
        "price": 57,
        "type": "חלבי",
        "Component": "מארז 15 יח' מכיל: 3 יח' גבינה עלים, 3 יח'  עלים תפוח אדמה, 3 יח' קשקבל, 3 יח' פיצה, 3 יח' יווני חצילים / פטריות",
        "image": "talzip_roladin-1-210726_hrz-1024x683.jpg"
    },
    {
        "id": 102,
        "name": "מאפים מלוחים",
        "description": "בורקס עלים גבינה",
        "price": 82,
        "type": "חלבי",
        "Component": " בורקס מבצק עלים במילוי  גבינות ",
        "image": "בורק-גבינה.png"
    },
    {
        "id": 123,
        "name": "מארזי מתנות",
        "description": "אירח מושלם",
        "price": 257,
        "type": "חלבי",
        "Component": "",
        "image": "אירוחמושלם.jpg"
    },
    {
        "id": 123456,
        "name": "מארזי מתנות",
        "description": "הכל בשבילך",
        "price": 170,
        "type": "חלבי",
        "Component": "",
        "image": "הכל בשבילך.jpg"
    },
    {
        "id": 444,
        "name": "מארזי מתנות",
        "description": "מארז יומולדת",
        "price": 36,
        "type": "",
        "Component": "",
        "image": "מארז יומולדת.jpg"
    },
    {
        "id": 111,
        "name": "מארזי מתנות",
        "description": "מארז ספר ועוגת דבש",
        "price": 412,
        "type": "פרווה",
        "Component": "",
        "image": "מארז ספר ועוגת דבש.jpg"
    },
    {
        "id": 222222,
        "name": "מארזי מתנות",
        "description": "מארז",
        "price": 99,
        "type": "פרווה",
        "Component": "",
        "image": "מארז.jpg"
    },
    {
        "id": 123654789,
        "name": "מארזי מתנות",
        "description": "עוגיות פקאן מושלגות",
        "price": 112,
        "type": "פרווה",
        "Component": "",
        "image": "1.png"
    },
    {
        "id": 147,
        "name": "מארזי מתנות",
        "description": "פינוקים ונהנים",
        "price": 112,
        "type": "פרווה",
        "Component": "",
        "image": "פינוקים ונהנים.jpg"
    },
    {
        "id": 40000,
        "name": "עוגות שמרים",
        "description": "בריוש ריקוטה",
        "price": 52,
        "type": "פרווה",
        "Component": "",
        "image": "בריוש ריקוטה.jpg"
    },
    {
        "id": 40002,
        "name": "עוגות שמרים",
        "description": "קראנץ אגוזים וקינמון ",
        "price": 49,
        "type": "חלבי",
        "Component": "",
        "image": "קראנץ אגוזים וקינמון חלבי.jpg"
    },
    {
        "id": 40003,
        "name": "עוגות שמרים",
        "description": "קראנץ חלווה ",
        "price": 49,
        "type": "חלבי",
        "Component": "",
        "image": "קראנץ חלווה 49.jpg"
    },
    {
        "id": 40004,
        "name": "עוגות שמרים",
        "description": "קראנץ שוקולד ",
        "price": 49,
        "type": "חלבי",
        "Component": "",
        "image": "קראנץ שוקולד 49.jpg"
    },
    {
        "id": 40005,
        "name": "עוגות שמרים",
        "description": "שטרודל גבינה ואוכמניות ",
        "price": 49,
        "type": "חלבי",
        "Component": "",
        "image": "שטרודל גבינה ואוכמניות 49.jpg"
    },
    {
        "id": 40006,
        "name": "עוגות שמרים",
        "description": "שטרודל תפוחים",
        "price": 52,
        "type": "פרווה",
        "Component": "",
        "image": "שטרודל תפוחים.jpg"
    },
    {
        "id": 1,
        "name": "משפחת לחם",
        "description": "בייגל - 5 יח'",
        "price": 32,
        "type": "פרווה",
        "Component": "",
        "image": "בייגל - 5 יח'.jpg"
    },
    {
        "id": 2,
        "name": "משפחת לחם",
        "description": "מקל פלוט גבינות וזיתים - 1 יח'",
        "price": 26,
        "type": "פרווה",
        "Component": "",
        "image": "מקל פלוט גבינות וזיתים - 1 יח'.jpg"
    },
    {
        "id": 3,
        "name": "משפחת לחם",
        "description": "מארז 3 יח' פלוט גבינות וזיתי קלמטה",
        "price": 20,
        "type": "פרווה",
        "Component": "",
        "image": "מארז 3 יח' פלוט גבינות וזיתי קלמטה.jpg"
    },
    {
        "id": 4,
        "name": "משפחת לחם",
        "description": "מארז בריוש קיראן - 5 יח'",
        "price": 28,
        "type": "פרווה",
        "Component": "",
        "image": "מארז בריוש קיראן - 5 יח'.jpg"
    },
    {
        "id": 7,
        "name": "משפחת לחם",
        "description": "מארז 5 יח' לחמניית ביס קמח לבן",
        "price": 25,
        "type": "פרווה",
        "Component": "",
        "image": "מארז 5 יח' לחמניית ביס קמח לבן.jpg"
    },
     {
        "id": 371,
        "name": "קישים",
        "description": "קיש בטטה (קוטר 22)",
        "price": 75,
        "image": "קיש_בטטה.jpg",
        "type": "חלבי",
        "Component": "בטטה צלויה בשמן זית ואגוזי מלך."     
    },
    {
        "id": 30259967,
        "name": "קישים",
        "description": "קיש בצלים (קוטר 22)",
        "price": 75,
        "image": "קיש_בצל.jpg",
        "type": "חלבי",
        "Component": "בצל לבן וסגול, כרישה, גבינה מלוחה."
    },
    {
        "id": 30551,
        "name": "קישים",
        "description": "קיש גרטן תפוא פטריות (קוטר 22)",
        "price": 75,
        "image": "קיש_פטריות.jpg",
        "type": "חלבי",
        "Component": "תפוחי אדמה ופטריות צלויות בשמן זית."
    },
    {
        "id": 31411,
        "name": "קישים",
        "description": "קיש מלנזנה ארביאטה (קוטר 22)",
        "price": 75,
        "image": "מלנזנה-ארביאטה-1024x683.jpg",
        "type": "חלבי",
        "Component": "חצילים ופלפלים קלויים, עגבניות ופלפל חריף."
    },
    {
        "id": 3555,
        "name": "קישים",
        "description": "קיש זוקיני תרד (קוטר 22)",
        "price": 75,
        "image": "talzip-roladin-1-23-4465-mrz-1024x683.jpg",
        "type": "חלבי",
        "Component": "תרד, זוקיני , אגוזי מלך וגבינת קשקבל."
    }
]